[
  {
    "id": "1",
    "title": "Test Alert 1",
    "date": "01/01/2020",
    "description": "This is the alert description this description will describe the alert",
    "author": "John Smith",
    "email": "jsmith@company.com",
    "active": "yes"
  },
  {
    "id": "2",
    "title": "Test Alert 2",
    "date": "01/01/2020",
    "description": "This is the alert description this description will describe the alert",
    "author": "John Smith",
    "email": "jsmith@company.com",
    "active": "yes"
  },
  {
    "id": "3",
    "title": "Test Alert 3",
    "date": "01/01/2020",
    "description": "This is the alert description this description will describe the alert",
    "author": "John Smith",
    "email": "jsmith@company.com",
    "active": "yes"
  },
  {
    "id": "4",
    "title": "Test Alert 4",
    "date": "01/01/2020",
    "description": "This is the alert description this description will describe the alert",
    "author": "John Smith",
    "email": "jsmith@company.com",
    "active": "yes"
  },
  {
    "id": "5",
    "title": "Test Alert 5",
    "date": "01/01/2020",
    "description": "This is the alert description this description will describe the alert",
    "author": "John Smith",
    "email": "jsmith@company.com",
    "active": "yes"
  },
  {
    "id": "6",
    "title": "Test Alert 6",
    "date": "01/01/2020",
    "description": "This is the alert description this description will describe the alert",
    "author": "John Smith",
    "email": "jsmith@company.com",
    "active": "yes"
  },
  {
    "id": "7",
    "title": "Test Alert 7",
    "date": "01/01/2020",
    "description": "This is the alert description this description will describe the alert",
    "author": "John Smith",
    "email": "jsmith@company.com",
    "active": "yes"
  },
  {
    "id": "8",
    "title": "Test Alert 8",
    "date": "01/01/2020",
    "description": "This is the alert description this description will describe the alert",
    "author": "John Smith",
    "email": "jsmith@company.com",
    "active": "yes"
  },
  {
    "id": "9",
    "title": "Test Alert 9",
    "date": "01/01/2020",
    "description": "This is the alert description this description will describe the alert",
    "author": "John Smith",
    "email": "jsmith@company.com",
    "active": "yes"
  },
  {
    "id": "10",
    "title": "Test Alert 10",
    "date": "01/01/2020",
    "description": "This is the alert description this description will describe the alert",
    "author": "John Smith",
    "email": "jsmith@company.com",
    "active": "yes"
  },
  {
    "id": "11",
    "title": "Test Alert 11",
    "date": "01/01/2020",
    "description": "This is the alert description this description will describe the alert",
    "author": "John Smith",
    "email": "jsmith@company.com",
    "active": "yes"
  },
  {
    "id": "12",
    "title": "New Alert Update POW POW",
    "date": "01.01.2020",
    "description": "This is the alert description this is what we do to update the alert",
    "author": "Ray Bayly",
    "email": "rbayly@company.com",
    "active": "No"
  },
  {
    "id": "13",
    "title": "Test Alert 13",
    "date": "01/01/2020",
    "description": "This is the alert description this description will describe the alert",
    "author": "John Smith",
    "email": "jsmith@company.com",
    "active": "yes"
  },
  {
    "id": "14",
    "title": "Test Alert 14",
    "date": "01/01/2020",
    "description": "This is the alert description this description will describe the alert",
    "author": "John Smith",
    "email": "jsmith@company.com",
    "active": "yes"
  },
  {
    "id": "15",
    "title": "Test Alert 15",
    "date": "01/01/2020",
    "description": "This is the alert description this description will describe the alert",
    "author": "John Smith",
    "email": "jsmith@company.com",
    "active": "yes"
  },
  {
    "id": "16",
    "title": "Test Alert 16",
    "date": "01/01/2020",
    "description": "This is the alert description this description will describe the alert",
    "author": "John Smith",
    "email": "jsmith@company.com",
    "active": "yes"
  },
  {
    "id": "17",
    "title": "Test Alert 17",
    "date": "01/01/2020",
    "description": "This is the alert description this description will describe the alert",
    "author": "John Smith",
    "email": "jsmith@company.com",
    "active": "yes"
  },
  {
    "id": "18",
    "title": "Test Alert 18",
    "date": "01/01/2020",
    "description": "This is the alert description this description will describe the alert",
    "author": "John Smith",
    "email": "jsmith@company.com",
    "active": "yes"
  },
  {
    "id": "19",
    "title": "Test Alert 19",
    "date": "01/01/2020",
    "description": "This is the alert description this description will describe the alert",
    "author": "John Smith",
    "email": "jsmith@company.com",
    "active": "yes"
  },
  {
    "id": "20",
    "title": "Test Alert 20",
    "date": "01/01/2020",
    "description": "This is the alert description this description will describe the alert",
    "author": "John Smith",
    "email": "jsmith@company.com",
    "active": "yes"
  },
  {
    "id": "21",
    "title": "Test Alert 21",
    "date": "01/01/2020",
    "description": "This is the alert description this description will describe the alert",
    "author": "John Smith",
    "email": "jsmith@company.com",
    "active": "yes"
  },
  {
    "id": 22,
    "title": "New Alert",
    "date": "01/1/2020",
    "description": "This is a new alert ",
    "author": "Raymond Bayly",
    "email": "jsmith@company.com",
    "active": "yes"
  },
  {
    "id": 23,
    "title": "New Alert",
    "date": "01/1/2020",
    "description": "This is a new alert ",
    "author": "Raymond Bayly",
    "email": "jsmith@company.com",
    "active": "yes"
  },
  {
    "id": 24,
    "title": "New Alert",
    "date": "01/1/2020",
    "description": "This is a new alert ",
    "author": "Raymond Bayly",
    "email": "jsmith@company.com",
    "active": "yes"
  },
  {
    "id": 25,
    "title": "New Alert",
    "date": "01/1/2020",
    "description": "This is a new alert ",
    "author": "Raymond Bayly",
    "email": "jsmith@company.com"
  }
]
